molangTest/test1.py
molangTest/test2.py
molangTest-0.0.0.1.dist-info/METADATA
molangTest-0.0.0.1.dist-info/WHEEL
molangTest-0.0.0.1.dist-info/top_level.txt
molangTest-0.0.0.1.dist-info/RECORD
