Metadata-Version: 2.1
Name: molangTest
Version: 0.0.0.1
Summary: My First Test Package
Home-page: https://lingua.blog.me/...
Author: Hyeongju Jeon
Author-email: a54841873@gmail.com
License: MIT
Requires-Python: >=3
